{
	"$schema": "https://biomejs.dev/schemas/2.4.4/schema.json",
	"vcs": {
		"enabled": true,
		"clientKind": "git",
		"useIgnoreFile": false
	},
	"files": {
		"ignoreUnknown": true,
		"includes": [
			"**",
			"!**/dist",
			"!**/examples",
			"!**/detectable.json",
			"!**/detectable_fixes.json"
		],
		"maxSize": 5242880
	},
	"formatter": {
		"enabled": true,
		"indentStyle": "tab",
		"lineEnding": "lf"
	},
	"assist": {
		"actions": {
			"source": {
				"organizeImports": "on"
			}
		}
	},
	"css": {
		"formatter": {
			"indentStyle": "tab",
			"lineEnding": "lf"
		}
	},
	"linter": {
		"enabled": true,
		"rules": {
			"recommended": true,
			"correctness": {
				"noUnusedImports": "error",
				"noUnusedVariables": "error",
				"noConstructorReturn": "off"
			},
			"suspicious": {
				"noVar": "error",
				"noExplicitAny": "warn",
				"noNonNullAssertedOptionalChain": "warn"
			},
			"style": {
				"useConst": "error",
				"noParameterAssign": "error",
				"useAsConstAssertion": "error",
				"useDefaultParameterLast": "error",
				"useEnumInitializers": "error",
				"useSelfClosingElements": "error",
				"useSingleVarDeclarator": "error",
				"noUnusedTemplateLiteral": "error",
				"useNumberNamespace": "error",
				"noInferrableTypes": "error",
				"noUselessElse": "error"
			}
		},
		"includes": ["**", "!**/types/**"]
	},
	"javascript": {
		"formatter": {
			"quoteStyle": "double",
			"indentStyle": "tab",
			"indentWidth": 4,
			"lineEnding": "lf",
			"semicolons": "always"
		}
	},
	"root": true
}
